Engine/Collider.py
Engine/Engine.py
Engine/Mathf.py
Engine/__init__.py
GameObject/GameObject.py
GameObject/Transform.py
GameObject/Vector2.py
GameObject/__init__.py
Timer/Time.py
Timer/__init__.py
mc_sprite-0.0.26.data/data/mc_sprite.py
mc_sprite-0.0.26.dist-info/METADATA
mc_sprite-0.0.26.dist-info/WHEEL
mc_sprite-0.0.26.dist-info/top_level.txt
mc_sprite-0.0.26.dist-info/RECORD
