Metadata-Version: 2.1
Name: mc-sprite
Version: 0.0.26
Summary: UNKNOWN
Home-page: https://www.coding4fun.com.cn/
Author: 魔扣少儿编程_Hugn
Author-email: UNKNOWN
License: UNKNOWN
Platform: UNKNOWN
Requires-Dist: pygame (>=1.9.4)
Requires-Dist: numpy (>=1.17.3)
